llama_index/tools/jira/__init__.py
llama_index/tools/jira/base.py
llama_index_tools_jira-0.2.1.dist-info/METADATA
llama_index_tools_jira-0.2.1.dist-info/WHEEL
llama_index_tools_jira-0.2.1.dist-info/licenses/LICENSE
llama_index_tools_jira-0.2.1.dist-info/RECORD
